README.rst
setup.py
ballpark/__init__.py
ballpark/notation.py
ballpark/shortcuts.py
ballpark/statistics.py
ballpark/tests.py
ballpark/utils.py
ballpark.egg-info/PKG-INFO
ballpark.egg-info/SOURCES.txt
ballpark.egg-info/dependency_links.txt
ballpark.egg-info/top_level.txt