Metadata-Version: 1.1
Name: ballpark
Version: 1.1.1
Summary: Better human-readable numbers.
Home-page: https://github.com/debrouwere/python-ballpark/
Author: Stijn Debrouwere
Author-email: stijn@debrouwere.org
License: ISC
Download-URL: https://www.github.com/debrouwere/python-ballpark/tarball/master
Keywords: human numbers format notation scientific engineering
Platform: UNKNOWN
Classifier: Development Status :: 4 - Beta
Classifier: Intended Audience :: Developers
Classifier: License :: OSI Approved :: ISC License (ISCL)
Classifier: Operating System :: OS Independent
Classifier: Topic :: Scientific/Engineering :: Information Analysis
Classifier: Topic :: Utilities
Classifier: Programming Language :: Python
Classifier: Programming Language :: Python :: 2
Classifier: Programming Language :: Python :: 2.7
Classifier: Programming Language :: Python :: 3
Classifier: Programming Language :: Python :: 3.4
